{"format":2,"version":"5.3.1","globals":"1c3d1ee36a85c1d0deff2775e68b2955","files":{"capasm___init___py":{"hash":"d00a488dd957ae91e7a5b602c30adc12","index":{"nums":[1,3,0,0,0,0,0],"html_filename":"capasm___init___py.html","relative_filename":"capasm/__init__.py"}},"capasm_assembler_py":{"hash":"e35feffae6f42001d37f75e1eed36d7c","index":{"nums":[1,246,34,2,0,0,0],"html_filename":"capasm_assembler_py.html","relative_filename":"capasm/assembler.py"}},"capasm_capcommon_py":{"hash":"f68867c767d81e7469827f4e242cc19f","index":{"nums":[1,1563,27,82,0,0,0],"html_filename":"capasm_capcommon_py.html","relative_filename":"capasm/capcommon.py"}},"capasm_captools_py":{"hash":"ab058efe57154969b745f60a4614af6e","index":{"nums":[1,600,79,57,0,0,0],"html_filename":"capasm_captools_py.html","relative_filename":"capasm/captools.py"}},"capasm_globals75_py":{"hash":"f281d79bd7087161fee983b0443a6940","index":{"nums":[1,9,0,1,0,0,0],"html_filename":"capasm_globals75_py.html","relative_filename":"capasm/globals75.py"}},"capasm_globals85_py":{"hash":"8b48732655da651de1379dafb7946f76","index":{"nums":[1,9,0,1,0,0,0],"html_filename":"capasm_globals85_py.html","relative_filename":"capasm/globals85.py"}},"capasm_globalsnone_py":{"hash":"2b31c3e8c164dddf0acb174314a8aea8","index":{"nums":[1,9,0,2,0,0,0],"html_filename":"capasm_globalsnone_py.html","relative_filename":"capasm/globalsnone.py"}},"capasm_ncas_py":{"hash":"20efb51eaefe45bfd528be6cbe0ec45d","index":{"nums":[1,716,33,88,0,0,0],"html_filename":"capasm_ncas_py.html","relative_filename":"capasm/ncas.py"}},"captest_py":{"hash":"42969d37462bcaebb3384e73535fb40f","index":{"nums":[1,73,0,8,0,0,0],"html_filename":"captest_py.html","relative_filename":"captest.py"}}}}